{
  "issueNumber": "20240615011171",
  "startTime": "2024-06-15 19:30:00",
  "endTime": "2024-06-15 19:31:00",
  "results": [
    {
      "issueNumber": "20240615011170",
      "premium": "81250"
    },
    {
      "issueNumber": "20240615011169",
      "premium": "99238"
    },
    {
      "issueNumber": "20240615011168",
      "premium": "88910"
    },
    {
      "issueNumber": "20240615011167",
      "premium": "21415"
    },
    {
      "issueNumber": "20240615011166",
      "premium": "49308"
    },
    {
      "issueNumber": "20240615011165",
      "premium": "55185"
    },
    {
      "issueNumber": "20240615011164",
      "premium": "31670"
    },
    {
      "issueNumber": "20240615011163",
      "premium": "10872"
    },
    {
      "issueNumber": "20240615011162",
      "premium": "56129"
    },
    {
      "issueNumber": "20240615011161",
      "premium": "50468"
    }
  ]
}